efel/DependencyV5.txt
efel/__init__.py
efel/_version.py
efel/api.py
efel/cppcore.cp310-win_amd64.pyd
efel/cppcore.pyi
efel/io.py
efel/settings.py
efel/cppcore/BasicFeatures.h
efel/cppcore/DependencyTree.h
efel/cppcore/EfelExceptions.h
efel/cppcore/FillFptrTable.h
efel/cppcore/Global.h
efel/cppcore/SpikeEvent.h
efel/cppcore/SpikeShape.h
efel/cppcore/Subthreshold.h
efel/cppcore/Utils.h
efel/cppcore/cfeature.h
efel/cppcore/eFELLogger.h
efel/cppcore/mapoperations.h
efel/cppcore/types.h
efel/pyfeatures/__init__.py
efel/pyfeatures/cppfeature_access.py
efel/pyfeatures/extrafeats.py
efel/pyfeatures/isi.py
efel/pyfeatures/multitrace.py
efel/pyfeatures/pyfeatures.py
efel/pyfeatures/validation.py
efel/units/__init__.py
efel/units/units.json
efel-5.7.20.dist-info/licenses/AUTHORS.txt
efel-5.7.20.dist-info/licenses/COPYING
efel-5.7.20.dist-info/licenses/COPYING.less
efel-5.7.20.dist-info/licenses/LICENSE.txt
efel-5.7.20.dist-info/METADATA
efel-5.7.20.dist-info/WHEEL
efel-5.7.20.dist-info/top_level.txt
efel-5.7.20.dist-info/RECORD
