Metadata-Version: 2.4
Name: efel
Version: 5.7.20
Summary: Electrophys Feature Extract Library (eFEL)
Home-page: https://github.com/openbraininstitute/eFEL
Author: BlueBrain Project, EPFL
Maintainer: Werner Van Geit
Maintainer-email: werner.vangeit@epfl.ch
License: LGPLv3
Keywords: feature,extraction,electrophysiology,BlueBrainProject
Classifier: Development Status :: 4 - Beta
Classifier: Environment :: Console
Classifier: License :: OSI Approved :: GNU Lesser General Public License v3 (LGPLv3)
Classifier: Programming Language :: Python
Classifier: Programming Language :: Python :: 3
Classifier: Operating System :: POSIX
Classifier: Topic :: Scientific/Engineering
Classifier: Topic :: Utilities
License-File: LICENSE.txt
License-File: COPYING
License-File: COPYING.less
License-File: AUTHORS.txt
Requires-Dist: numpy>=1.6
Requires-Dist: neo>=0.5.2
Requires-Dist: pynwb>=2.6.0
Requires-Dist: typing-extensions>=4.8.0
Requires-Dist: scipy<2.0.0,>=1.12.0
Dynamic: author
Dynamic: classifier
Dynamic: description
Dynamic: description-content-type
Dynamic: home-page
Dynamic: keywords
Dynamic: license
Dynamic: license-file
Dynamic: maintainer
Dynamic: maintainer-email
Dynamic: requires-dist
Dynamic: summary
